Workbook

Sheet Schedule
A1: MARTA VENTURES — DETAILED SCHEDULE 2026 (v4.1)
A3: Week | B3: Date | C3: BU | D3: Milestone | E3: Action Items | F3: Budget | G3: Gate | H3: Status
A4: W1 | B4: Jan 1-5 | C4: ALL | D4: Autónomo Registration | E4: Hacienda + RETA (no padrón needed) | F4: €0 | G4: G1
A5: W2 | B5: Jan 6-12 | C5: B | D5: Digital Presence | E5: Website + Instagram live | F5: €150 | G5: B1
A6: W3 | B6: Jan 13-19 | C6: B | D6: Print Production | E6: Order initial prints (20 pcs) | F6: €300 | G6: B1
A7: W4 | B7: Jan 20-26 | C7: A | D7: Trip Planning | E7: Book Mexico flights + hotels | F7: €0
A8: W5 | B8: Jan 27-31 | C8: ALL | D8: Housing + Padrón | E8: Sign contract, empadronamiento | F8: €0
A9: W6 | B9: Feb 1-7 | C9: ALL | D9: Healthcare + Gestor | E9: TSI card, contract gestor | F9: €80
A10: W7 | B10: Feb 8-14 | C10: ALL | D10: Travel to Mexico | E10: Depart Barcelona Feb 14 | F10: €0
A11: W8 | B11: Feb 15-21 | C11: A | D11: OAXACA SOURCING | E11: Alebrijes, textiles, pottery | F11: €1,100 | G11: A2
A12: W9 | B12: Feb 22-28 | C12: A | D12: PUEBLA + CDMX | E12: Talavera, books, return | F12: €1,100 | G12: A2
A13: W10 | B13: Mar 1-3 | C13: A | D13: Inventory Processing | E13: Photo, price, tag all items | F13: €0
A14: W10 | B14: Mar 4-8 | C14: ALL | D14: ARCO Madrid | E14: Gallery networking | F14: €350
A15: W11 | B15: Mar 9-14 | C15: A/B | D15: Market Prep | E15: Display setup, permits | F15: €160
A16: W12 | B16: Mar 15 | C16: A/B | D16: FIRST MARKET | E16: Sant Antoni launch | F16: €150 | G16: A3/B2/G2
A17: W13 | B17: Mar 16-22 | C17: A/B | D17: Second Market | E17: Try Els Encants | F17: €100
A18: W14 | B18: Mar 23-31 | C18: ALL | D18: Q1 Review | E18: Financial review, adjust | F18: €0 | G18: G2
A19: W15-17 | B19: Apr 1-21 | C19: A/B | D19: April Markets | E19: Regular schedule | F19: €300 | G19: B3
A20: W18-21 | B20: Apr 22-May 31 | C20: A/B | D20: Build Momentum | E20: Gallery outreach | F20: €400
A21: W22-26 | B21: Jun 1-30 | C21: A/B | D21: PEAK SEASON | E21: Maximum presence | F21: €400 | G21: G4/A4/B4

Sheet Sim_Commercio
A1: PLAN A: COMMERCIO — Revenue Simulator
A3: Enter your actual inventory items and costs below (blue cells = input)
A5: Item | B5: Category | C5: Cost (€) | D5: Sell Price (€) | E5: Qty | F5: Total Cost | G5: Total Revenue | H5: Margin %
A6: Alebrije - Jaguar | B6: Alebrijes | C6: 25 | D6: 80 | E6: 5 | F6: =IF(C6="","",C6*E6) -> 125 | G6: =IF(D6="","",D6*E6) -> 400 | H6: =IF(OR(C6="",D6=""),"",(D6-C6)/D6) -> 0.6875
A7: Alebrije - Dragon | B7: Alebrijes | C7: 30 | D7: 95 | E7: 3 | F7: =IF(C7="","",C7*E7) -> 90 | G7: =IF(D7="","",D7*E7) -> 285 | H7: =IF(OR(C7="",D7=""),"",(D7-C7)/D7) -> 0.68421053
A8: Talavera Plate Large | B8: Ceramics | C8: 35 | D8: 120 | E8: 4 | F8: =IF(C8="","",C8*E8) -> 140 | G8: =IF(D8="","",D8*E8) -> 480 | H8: =IF(OR(C8="",D8=""),"",(D8-C8)/D8) -> 0.70833333
A9: Talavera Vase | B9: Ceramics | C9: 40 | D9: 130 | E9: 3 | F9: =IF(C9="","",C9*E9) -> 120 | G9: =IF(D9="","",D9*E9) -> 390 | H9: =IF(OR(C9="",D9=""),"",(D9-C9)/D9) -> 0.69230769
A10: Rebozo Traditional | B10: Textiles | C10: 45 | D10: 150 | E10: 4 | F10: =IF(C10="","",C10*E10) -> 180 | G10: =IF(D10="","",D10*E10) -> 600 | H10: =IF(OR(C10="",D10=""),"",(D10-C10)/D10) -> 0.7
A11: Embroidered Blouse | B11: Textiles | C11: 30 | D11: 100 | E11: 5 | F11: =IF(C11="","",C11*E11) -> 150 | G11: =IF(D11="","",D11*E11) -> 500 | H11: =IF(OR(C11="",D11=""),"",(D11-C11)/D11) -> 0.7
A12: Art Book - Frida | B12: Books | C12: 15 | D12: 45 | E12: 6 | F12: =IF(C12="","",C12*E12) -> 90 | G12: =IF(D12="","",D12*E12) -> 270 | H12: =IF(OR(C12="",D12=""),"",(D12-C12)/D12) -> 0.66666667
A13: Art Book - Oaxaca | B13: Books | C13: 18 | D13: 50 | E13: 4 | F13: =IF(C13="","",C13*E13) -> 72 | G13: =IF(D13="","",D13*E13) -> 200 | H13: =IF(OR(C13="",D13=""),"",(D13-C13)/D13) -> 0.64
F14: =IF(C14="","",C14*E14) | G14: =IF(D14="","",D14*E14) | H14: =IF(OR(C14="",D14=""),"",(D14-C14)/D14)
F15: =IF(C15="","",C15*E15) | G15: =IF(D15="","",D15*E15) | H15: =IF(OR(C15="",D15=""),"",(D15-C15)/D15)
F16: =IF(C16="","",C16*E16) | G16: =IF(D16="","",D16*E16) | H16: =IF(OR(C16="",D16=""),"",(D16-C16)/D16)
F17: =IF(C17="","",C17*E17) | G17: =IF(D17="","",D17*E17) | H17: =IF(OR(C17="",D17=""),"",(D17-C17)/D17)
F18: =IF(C18="","",C18*E18) | G18: =IF(D18="","",D18*E18) | H18: =IF(OR(C18="",D18=""),"",(D18-C18)/D18)
F19: =IF(C19="","",C19*E19) | G19: =IF(D19="","",D19*E19) | H19: =IF(OR(C19="",D19=""),"",(D19-C19)/D19)
F20: =IF(C20="","",C20*E20) | G20: =IF(D20="","",D20*E20) | H20: =IF(OR(C20="",D20=""),"",(D20-C20)/D20)
F21: =IF(C21="","",C21*E21) | G21: =IF(D21="","",D21*E21) | H21: =IF(OR(C21="",D21=""),"",(D21-C21)/D21)
F22: =IF(C22="","",C22*E22) | G22: =IF(D22="","",D22*E22) | H22: =IF(OR(C22="",D22=""),"",(D22-C22)/D22)
F23: =IF(C23="","",C23*E23) | G23: =IF(D23="","",D23*E23) | H23: =IF(OR(C23="",D23=""),"",(D23-C23)/D23)
F24: =IF(C24="","",C24*E24) | G24: =IF(D24="","",D24*E24) | H24: =IF(OR(C24="",D24=""),"",(D24-C24)/D24)
F25: =IF(C25="","",C25*E25) | G25: =IF(D25="","",D25*E25) | H25: =IF(OR(C25="",D25=""),"",(D25-C25)/D25)
... F33: =IF(C33="","",C33*E33) | G33: =IF(D33="","",D33*E33) | H33: =IF(OR(C33="",D33=""),"",(D33-C33)/D33)
A36: SUMMARY
A37: Total Items | B37: =COUNTA(A6:A33) -> 8
A38: Total Quantity | B38: =SUM(E6:E33) -> 34
A39: Total Cost | B39: =SUM(F6:F33) -> 967
A40: Total Revenue (if all sold) | B40: =SUM(G6:G33) -> 3125
A41: Average Margin | B41: =IFERROR(AVERAGE(H6:H33),"") -> 0.68487728
A42: Gross Profit (if all sold) | B42: =G40-F39 -> 0
A46: MONTHLY PROJECTION
A47: Sell-through rate/month (%): | B47: 0.15
A48: Stall fees/month: | B48: 150
A49: Est. Monthly Revenue: | B49: =G40*B47 -> 0
A50: Est. Monthly Gross Profit: | B50: =B49*B41-B48 -> -150

Sheet Sim_Artistico
A1: PLAN B: ARTISTICO — Revenue Simulator
A3: Enter your prints and services below
A5: Print Name | B5: Size | C5: Print Cost (€) | D5: Sell Price (€) | E5: Qty Available | F5: Total Cost | G5: Potential Revenue
A6: Barcelona Gothic | B6: A3 | C6: 15 | D6: 120 | E6: 3 | F6: =IF(C6="","",C6*E6) -> 45 | G6: =IF(D6="","",D6*E6) -> 360
A7: Oaxaca Colors | B7: A3 | C7: 15 | D7: 120 | E7: 3 | F7: =IF(C7="","",C7*E7) -> 45 | G7: =IF(D7="","",D7*E7) -> 360
A8: Mexico City Night | B8: A2 | C8: 25 | D8: 200 | E8: 2 | F8: =IF(C8="","",C8*E8) -> 50 | G8: =IF(D8="","",D8*E8) -> 400
A9: Portrait Series #1 | B9: A2 | C9: 25 | D9: 250 | E9: 2 | F9: =IF(C9="","",C9*E9) -> 50 | G9: =IF(D9="","",D9*E9) -> 500
A10: Limited Edition #1 | B10: Large | C10: 40 | D10: 400 | E10: 1 | F10: =IF(C10="","",C10*E10) -> 40 | G10: =IF(D10="","",D10*E10) -> 400
F11: =IF(C11="","",C11*E11) | G11: =IF(D11="","",D11*E11)
F12: =IF(C12="","",C12*E12) | G12: =IF(D12="","",D12*E12)
F13: =IF(C13="","",C13*E13) | G13: =IF(D13="","",D13*E13)
F14: =IF(C14="","",C14*E14) | G14: =IF(D14="","",D14*E14)
F15: =IF(C15="","",C15*E15) | G15: =IF(D15="","",D15*E15)
F16: =IF(C16="","",C16*E16) | G16: =IF(D16="","",D16*E16)
F17: =IF(C17="","",C17*E17) | G17: =IF(D17="","",D17*E17)
F18: =IF(C18="","",C18*E18) | G18: =IF(D18="","",D18*E18)
F19: =IF(C19="","",C19*E19) | G19: =IF(D19="","",D19*E19)
F20: =IF(C20="","",C20*E20) | G20: =IF(D20="","",D20*E20)
F21: =IF(C21="","",C21*E21) | G21: =IF(D21="","",D21*E21)
F22: =IF(C22="","",C22*E22) | G22: =IF(D22="","",D22*E22)
... F25: =IF(C25="","",C25*E25) | G25: =IF(D25="","",D25*E25)
A28: SERVICES (Optional)
A29: Service | B29: Price (€) | C29: Est. Jobs/Month | D29: Monthly Revenue
A30: Family Portrait Session | B30: 250 | C30: 1 | D30: =B30*C30 -> 250
A31: Event Photography | B31: 300 | C31: 0.5 | D31: =B31*C31 -> 150
A32: Corporate Headshots | B32: 200 | C32: 1 | D32: =B32*C32 -> 200
A36: MONTHLY PROJECTION
A37: Print sales/month (%): | B37: 0.1
A38: Print Revenue/month: | B38: =SUM(G6:G26)*B37 -> 202
A39: Service Revenue/month: | B39: =SUM(D30:D32) -> 600
A40: Total Est. Revenue/month: | B40: =B38+B39 -> 802

Sheet Sim_Professionale
A1: PLAN C: PROFESSIONALE — Revenue Simulator (Optional)
A3: Use this to project film lab revenue IF you activate this business line
A5: Service | B5: Price (€) | C5: Cost/Unit (€) | D5: Est. Rolls/Month | E5: Monthly Revenue | F5: Monthly Cost | G5: Gross Profit
A6: B&W Develop + Scan | B6: 15 | C6: 6.75 | D6: 20 | E6: =B6*D6 -> 300 | F6: =C6*D6 -> 135 | G6: =E6-F6 -> 165
A7: C-41 Develop + Scan | B7: 18 | C7: 9 | D7: 15 | E7: =B7*D7 -> 270 | F7: =C7*D7 -> 135 | G7: =E7-F7 -> 135
A8: E-6 Develop + Scan | B8: 22 | C8: 12 | D8: 5 | E8: =B8*D8 -> 110 | F8: =C8*D8 -> 60 | G8: =E8-F8 -> 50
A9: Rush Service (+50%) | B9: 0 | C9: 0 | D9: 0 | E9: =B9*D9 -> 0 | F9: =C9*D9 -> 0 | G9: =E9-F9 -> 0
A12: WORKSHOPS
A13: Workshop | B13: Price/Person | C13: Attendees | D13: Sessions/Month | E13: Monthly Revenue
A14: Intro to Film | B14: 60 | C14: 4 | D14: 2 | E14: =B14*C14*D14 -> 480
A15: Photo Walk | B15: 45 | C15: 6 | D15: 4 | E15: =B15*C15*D15 -> 1080
A16: Darkroom Basics | B16: 80 | C16: 3 | D16: 1 | E16: =B16*C16*D16 -> 240
A20: MONTHLY SUMMARY
A21: Lab Revenue: | B21: =SUM(E6:E9) -> 680
A22: Lab Costs: | B22: =SUM(F6:F9) -> 330
A23: Workshop Revenue: | B23: =SUM(E14:E16) -> 1800
A24: Total Revenue: | B24: =B21+B23 -> 2480
A25: Total Gross Profit: | B25: =B24-B22 -> 2150

Sheet Transaction_Book
A1: MARTA VENTURES — TRANSACTION BOOK (v4.1)
A2: Record ALL income and expenses here. This is your financial truth.
A4: Date | B4: BU | C4: Type | D4: Category | E4: Description | F4: Income (€) | G4: Expense (€) | H4: Balance | I4: Notes
A5: 2026-01-01 | B5: ALL | C5: OPENING | D5: Capital | E5: Initial Capital | F5: 10000 | G5: 0 | H5: =F5-G5 -> 10000 | I5: Starting balance
A6: 2026-01-03 | B6: ALL | C6: EXPENSE | D6: Setup | E6: Website domain + hosting | G6: 120 | H6: =H5+F6-G6 -> 9880
A7: 2026-01-05 | B7: ALL | C7: EXPENSE | D7: Setup | E7: Business cards | G7: 30 | H7: =H6+F7-G7 -> 9850
A8: 2026-01-18 | B8: B | C8: EXPENSE | D8: Inventory | E8: Print batch #1 (20 prints) | G8: 300 | H8: =H7+F8-G8 -> 9550
A9: 2026-02-01 | B9: ALL | C9: EXPENSE | D9: Operating | E9: Social Security (Feb) | G9: 80 | H9: =H8+F9-G9 -> 9470
A10: 2026-02-01 | B10: ALL | C10: EXPENSE | D10: Operating | E10: Gestor (Feb) | G10: 50 | H10: =H9+F10-G10 -> 9420
A11: 2026-02-14 | B11: A | C11: EXPENSE | D11: Travel | E11: Mexico flights | G11: 900 | H11: =H10+F11-G11 -> 8520
A12: 2026-02-15 | B12: A | C12: EXPENSE | D12: Travel | E12: Mexico hotels | G12: 450 | H12: =H11+F12-G12 -> 8070
A13: 2026-02-28 | B13: A | C13: EXPENSE | D13: Inventory | E13: Mexico sourcing - Oaxaca | G13: 1200 | H13: =H12+F13-G13 -> 6870
A14: 2026-02-28 | B14: A | C14: EXPENSE | D14: Inventory | E14: Mexico sourcing - Puebla | G14: 500 | H14: =H13+F14-G14 -> 6370
A15: 2026-02-28 | B15: A | C15: EXPENSE | D15: Inventory | E15: Mexico sourcing - books | G15: 200 | H15: =H14+F15-G15 -> 6170
A16: 2026-03-01 | B16: ALL | C16: EXPENSE | D16: Operating | E16: Social Security (Mar) | G16: 80 | H16: =H15+F16-G16 -> 6090
A17: 2026-03-01 | B17: ALL | C17: EXPENSE | D17: Operating | E17: Gestor (Mar) | G17: 50 | H17: =H16+F17-G17 -> 6040
... A20: 2026-03-15 | B20: A | C20: EXPENSE | D20: Operating | E20: Sant Antoni stall fee | G20: 150 | H20: =H19+F20-G20 -> 5410
A21: 2026-03-15 | B21: A | C21: INCOME | D21: Sales | E21: Market - alebrije x2 | F21: 160 | H21: =H20+F21-G21 -> 5570
A22: 2026-03-15 | B22: B | C22: INCOME | D22: Sales | E22: Market - print A3 | F22: 120 | H22: =H21+F22-G22 -> 5690
H23: =H22+F23-G23 -> 5690
H24: =H23+F24-G24 -> 5690
H25: =H24+F25-G25 -> 5690
H26: =H25+F26-G26 -> 5690
H27: =H26+F27-G27 -> 5690
H28: =H27+F28-G28 -> 5690
H29: =H28+F29-G29 -> 5690
H30: =H29+F30-G30 -> 5690
H31: =H30+F31-G31 -> 5690
H32: =H31+F32-G32 -> 5690
H33: =H32+F33-G33 -> 5690
H34: =H33+F34-G34 -> 5690
... H205: =H204+F205-G205 -> 5690

Sheet Dashboard
A1: MARTA VENTURES — FINANCIAL DASHBOARD (v4.1)
A3: SUMMARY BY BUSINESS UNIT
A4: Business Unit | B4: Total Income | C4: Total Expenses | D4: Net | E4: Budget | F4: Remaining
A5: A - Commercio | B5: =SUMIF(Transaction_Book!B:B,"A",Transaction_Book!F:F) -> 160 | C5: =SUMIF(Transaction_Book!B:B,"A",Transaction_Book!G:G) -> 3530 | D5: =B5-C5 -> -3370 | E5: 5500 | F5: =E5-C5 -> 1970
A6: B - Artistico | B6: =SUMIF(Transaction_Book!B:B,"B",Transaction_Book!F:F) -> 120 | C6: =SUMIF(Transaction_Book!B:B,"B",Transaction_Book!G:G) -> 300 | D6: =B6-C6 -> -180 | E6: 1000 | F6: =E6-C6 -> 700
A7: C - Professionale | B7: =SUMIF(Transaction_Book!B:B,"C",Transaction_Book!F:F) -> 0 | C7: =SUMIF(Transaction_Book!B:B,"C",Transaction_Book!G:G) -> 0 | D7: =B7-C7 -> 0 | E7: 0 | F7: =E7-C7 -> 0
A8: ALL - Shared | B8: =SUMIF(Transaction_Book!B:B,"ALL",Transaction_Book!F:F) -> 10000 | C8: =SUMIF(Transaction_Book!B:B,"ALL",Transaction_Book!G:G) -> 760 | D8: =B8-C8 -> 9240 | E8: 3500 | F8: =E8-C8 -> 2740
A9: TOTAL | B9: =SUM(B5:B8) -> 10280 | C9: =SUM(C5:C8) -> 4590 | D9: =B9-C9 -> 5690 | E9: 10000 | F9: =E9-C9 -> 5410
A12: KEY METRICS
A13: Current Balance | B13: =Transaction_Book!H205 -> 5690
A14: Global Reserve Target | B14: 3000
A15: Reserve Status | B15: =IF(B13>=B14,"OK","WARNING") -> OK
A16: Total Income YTD | B16: =B9 -> 10280
A17: Total Expenses YTD | B17: =C9 -> 4590
A18: Net Profit/Loss | B18: =D9 -> 5690
A21: GATE STATUS (Update Manually)
A22: Gate | B22: Target Date | C22: Status | D22: Notes
A23: G1: Launch | B23: Jan 5
A24: G2: First Revenue | B24: Mar 31
A25: A2: Mexico Trip | B25: Feb 28
A26: B1: Portfolio | B26: Jan 12
A27: A3/B2: First Market | B27: Mar 15

Sheet Instructions
A1: HOW TO USE THIS WORKBOOK
A4: BLUE CELLS = INPUT (you fill these in)
A5: WHITE CELLS = FORMULAS (don't edit)
A6: GREEN CELLS = KEY TOTALS
A8: ═══════════════════════════════════════════════════════════
A10: SCHEDULE TAB:
A11: • Track progress against the plan
A12: • Update Status column as you complete items
A13: • Use dropdowns: NOT STARTED, IN PROGRESS, DONE, BLOCKED
A15: SIMULATOR TABS (Sim_Commercio, Sim_Artistico, Sim_Professionale):
A16: • Enter your ACTUAL items with real costs and prices
A17: • Simulator calculates margins and projections
... A48: 3. Adjust simulators for next quarter
